pytest_jsonschema_snapshot/__init__.py
pytest_jsonschema_snapshot/core.py
pytest_jsonschema_snapshot/plugin.py
pytest_jsonschema_snapshot/py.typed
pytest_jsonschema_snapshot/stats.py
pytest_jsonschema_snapshot/tools/__init__.py
pytest_jsonschema_snapshot/tools/name_maker.py
pytest_jsonschema_snapshot/tools/genson_addon/__init__.py
pytest_jsonschema_snapshot/tools/genson_addon/format_detector.py
pytest_jsonschema_snapshot/tools/genson_addon/to_schema_converter.py
pytest_jsonschema_snapshot-0.2.3.dist-info/METADATA
pytest_jsonschema_snapshot-0.2.3.dist-info/WHEEL
pytest_jsonschema_snapshot-0.2.3.dist-info/entry_points.txt
pytest_jsonschema_snapshot-0.2.3.dist-info/licenses/LICENSE
pytest_jsonschema_snapshot-0.2.3.dist-info/RECORD
