Metadata-Version: 2.4
Name: pytest-jsonschema-snapshot
Version: 0.2.3
Summary: Pytest plugin for automatic JSON Schema generation and validation from examples
Project-URL: Homepage, https://miskler.github.io/pytest-jsonschema-snapshot/basic/quick_start.html
Project-URL: Repository, https://github.com/Miskler/pytest-jsonschema-snapshot
Project-URL: Documentation, https://miskler.github.io/pytest-jsonschema-snapshot/basic/quick_start.html
Project-URL: Issues, https://github.com/Miskler/pytest-jsonschema-snapshot/issues
Author: Miskler
License: MIT
License-File: LICENSE
Keywords: genson,json,pytest,rich,schema,validation
Classifier: Intended Audience :: Developers
Classifier: License :: OSI Approved :: MIT License
Classifier: Operating System :: Microsoft :: Windows
Classifier: Operating System :: POSIX :: Linux
Classifier: Programming Language :: Python :: 3
Classifier: Programming Language :: Python :: 3.10
Classifier: Programming Language :: Python :: 3.11
Classifier: Programming Language :: Python :: 3.12
Classifier: Programming Language :: Python :: 3.13
Classifier: Topic :: Software Development :: Libraries :: Python Modules
Classifier: Topic :: Utilities
Requires-Python: >=3.10
Requires-Dist: genson
Requires-Dist: jsonschema
Requires-Dist: jsonschema-diff
Requires-Dist: pathvalidate
Requires-Dist: pytest
Provides-Extra: dev
Requires-Dist: black; extra == 'dev'
Requires-Dist: docutils; extra == 'dev'
Requires-Dist: flake8; extra == 'dev'
Requires-Dist: furo; extra == 'dev'
Requires-Dist: isort; extra == 'dev'
Requires-Dist: mypy; extra == 'dev'
Requires-Dist: pytest-asyncio; extra == 'dev'
Requires-Dist: pytest-cov; extra == 'dev'
Requires-Dist: pytest-xdist; extra == 'dev'
Requires-Dist: sphinx; extra == 'dev'
Requires-Dist: sphinx-autoapi; extra == 'dev'
Requires-Dist: types-docutils; extra == 'dev'
Requires-Dist: types-jsonschema; extra == 'dev'
